scraper_bcv/__init__.py
scraper_bcv/__main__.py
scraper_bcv/bcv_client.py
scraper_bcv/cli.py
scraper_bcv-0.1.1.dist-info/METADATA
scraper_bcv-0.1.1.dist-info/WHEEL
scraper_bcv-0.1.1.dist-info/entry_points.txt
scraper_bcv-0.1.1.dist-info/top_level.txt
scraper_bcv-0.1.1.dist-info/RECORD
