Metadata-Version: 2.4
Name: scraper-bcv
Version: 0.1.1
Summary: Cliente Python para obtener datos del BCV con trazabilidad y cumplimiento legal
Home-page: https://github.com/fquivera/scraper-bcv
Author: Francisco Antonio Quivera González
Author-email: fquivera@gmail.com
License: MIT
Classifier: Development Status :: 5 - Production/Stable
Classifier: Intended Audience :: Developers
Classifier: License :: OSI Approved :: MIT License
Classifier: Programming Language :: Python :: 3
Classifier: Programming Language :: Python :: 3.9
Classifier: Programming Language :: Python :: 3.10
Classifier: Programming Language :: Python :: 3.11
Classifier: Programming Language :: Python :: 3.12
Classifier: Operating System :: OS Independent
Classifier: Topic :: Software Development :: Libraries
Classifier: Topic :: Office/Business :: Financial
Requires-Python: >=3.9
Requires-Dist: requests>=2.32
Requires-Dist: beautifulsoup4>=4.13
Provides-Extra: dev
Requires-Dist: pytest>=8.0; extra == "dev"
Requires-Dist: pytest-cov>=6.0; extra == "dev"
Requires-Dist: build; extra == "dev"
Requires-Dist: twine; extra == "dev"
Requires-Dist: playwright; extra == "dev"
Requires-Dist: black; extra == "dev"
Requires-Dist: flake8; extra == "dev"
Requires-Dist: mypy; extra == "dev"
